bear_lake/__init__.py
bear_lake/connection.py
bear_lake/database.py
bear_lake/table.py
bear_lake/filesystem_client/__init__.py
bear_lake/filesystem_client/base.py
bear_lake/filesystem_client/local_client.py
bear_lake/filesystem_client/s3_client.py
bear_lake-0.1.5.dist-info/METADATA
bear_lake-0.1.5.dist-info/WHEEL
bear_lake-0.1.5.dist-info/top_level.txt
bear_lake-0.1.5.dist-info/RECORD
