Metadata-Version: 2.4
Name: bear-lake
Version: 0.1.5
Summary: A lightweight, file-based database built on Polars and Parquet, designed for fast analytics and easy data management.
Requires-Python: >=3.10
Requires-Dist: polars>=1.36.1
Requires-Dist: pyarrow>=18.1.0
Requires-Dist: s3fs>=2025.12.0
Requires-Dist: tqdm>=4.67.1
